dictionary_diff/__init__.py
dictionary_diff/change.py
dictionary_diff/dict_diff.py
dictionary_diff/diff.py
dictionary_diff/list_diff.py
tests/__init__.py
tests/profile_dict_diff.py
tests/test_dict_diff.py
dictionary_diff-0.0.2.dist-info/LICENSE
dictionary_diff-0.0.2.dist-info/METADATA
dictionary_diff-0.0.2.dist-info/WHEEL
dictionary_diff-0.0.2.dist-info/top_level.txt
dictionary_diff-0.0.2.dist-info/RECORD
