Metadata-Version: 2.1
Name: dictionary-diff
Version: 0.0.2
Summary: Get and apply diffs of python dictionaries
Home-page: https://github.com/JanLukasGithub/dict-diff
Author: Jan Lukas
Author-email: jan@garloff.de
Project-URL: Bug Tracker, https://github.com/JanLukasGithub/dict-diff/issues
Classifier: Programming Language :: Python :: 3
Classifier: License :: OSI Approved :: MIT License
Classifier: Operating System :: OS Independent
Requires-Python: >=3.8
License-File: LICENSE
